pymoa/__init__.py
pymoa/base.py
pymoa/data_logger.py
pymoa/utils.py
pymoa/device/__init__.py
pymoa/device/adc.py
pymoa/device/analog.py
pymoa/device/digital.py
pymoa/device/port.py
pymoa/stage/__init__.py
pymoa/stage/delay.py
pymoa/stage/gate.py
pymoa/tests/__init__.py
pymoa/tests/conftest.py
pymoa-1.0.0.dist-info/licenses/LICENSE
pymoa-1.0.0.dist-info/METADATA
pymoa-1.0.0.dist-info/WHEEL
pymoa-1.0.0.dist-info/top_level.txt
pymoa-1.0.0.dist-info/RECORD
